verry-0.4.1.dist-info/RECORD
verry-0.4.1.dist-info/WHEEL
verry-0.4.1.dist-info/METADATA
verry-0.4.1.dist-info/licenses/LICENSE.txt
verry/__init__.py
verry/affineform.py
verry/typing.py
verry/function.py
verry/intervalseries.py
verry/misc/__init__.py
verry/misc/formatspec.py
verry/linalg/__init__.py
verry/linalg/intervalmatrix.py
verry/linalg/floatintervalmatrix.py
verry/optimize/optimize.py
verry/optimize/__init__.py
verry/optimize/rootfinding.py
verry/autodiff/__init__.py
verry/autodiff/dual.py
verry/autodiff/autodiff.py
verry/integrate/quad.py
verry/integrate/integrator.py
verry/integrate/_impl.py
verry/integrate/solver.py
verry/integrate/vareqsolver.py
verry/integrate/__init__.py
verry/integrate/tracker.py
verry/interval/CMakeLists.txt
verry/interval/interval.py
verry/interval/__init__.py
verry/interval/_floatoperator.cpython-313-darwin.so
verry/interval/_floatoperator.cpp
verry/interval/floatinterval.py
verry/interval/_floatoperator.pyi
