Metadata-Version: 2.2
Name: verry
Version: 0.4.1
Summary: An open-source package for verified computation written in Python.
Author-Email: Ryoga Iwanami <iwanami.ryoga@akane.waseda.jp>
License: BSD 3-Clause License
Classifier: Development Status :: 3 - Alpha
Classifier: Intended Audience :: Developers
Classifier: Intended Audience :: Science/Research
Classifier: License :: OSI Approved :: BSD License
Classifier: Programming Language :: C++
Classifier: Programming Language :: Python :: 3.13
Classifier: Topic :: Scientific/Engineering :: Mathematics
Project-URL: homepage, https://python-verry.github.io/verry
Project-URL: source, https://github.com/python-verry/verry
Requires-Python: >=3.13
Requires-Dist: gmpy2>=2.2.1
Requires-Dist: mpmath>=1.3.0
Requires-Dist: numpy>=2.2.5
